GalileoFlowSDK/GalileoFlowSdk.py
GalileoFlowSDK/__init__.py
galileoflowsdk-0.1.8.dist-info/METADATA
galileoflowsdk-0.1.8.dist-info/WHEEL
galileoflowsdk-0.1.8.dist-info/top_level.txt
galileoflowsdk-0.1.8.dist-info/RECORD
