Metadata-Version: 2.4
Name: galileoflowsdk
Version: 0.1.8
Summary: Reading a flow rate from Galileo Flow Sensor
Author: Galileo (MIC)
Author-email: <galileo@microfluidic.fr>
Keywords: python,galileo
Requires-Dist: pyserial
Dynamic: author
Dynamic: author-email
Dynamic: description
Dynamic: description-content-type
Dynamic: keywords
Dynamic: requires-dist
Dynamic: summary
